pyhcal/ERROR.FIL
pyhcal/__init__.py
pyhcal/calibrators.py
pyhcal/figures.py
pyhcal/mappers.py
pyhcal/metrics.py
pyhcal/repository.py
pyhcal/setup_utils.py
pyhcal/data/HUC_Names.csv
pyhcal-1.1.3.dist-info/METADATA
pyhcal-1.1.3.dist-info/WHEEL
pyhcal-1.1.3.dist-info/RECORD
