Metadata-Version: 2.4
Name: pyhcal
Version: 1.1.3
Summary: Python package for calibrating MPCA HSPF models
Project-URL: Homepage, https://github.com/mfratkin1/pyhcal
Author-email: Mulu Fratkin <michael.fratkin@state.mn.us>
Maintainer-email: Mulu Fratkin <michael.fratkin@state.mn.us>
License-Expression: MIT
Keywords: HSPF,Hydrology
Classifier: Development Status :: 3 - Alpha
Classifier: Programming Language :: Python
Requires-Python: >=3.8
Requires-Dist: geopandas
Requires-Dist: hspf
Requires-Dist: matplotlib
Requires-Dist: mpcahydro
Requires-Dist: scipy
